_pybgpstream.cpython-37m-darwin.so
pybgpstream/__init__.py
pybgpstream/pybgpstream.py
pybgpstream/test_pybgpstream.py
pybgpstream-2.0.2.dist-info/AUTHORS
pybgpstream-2.0.2.dist-info/AUTHORS.md
pybgpstream-2.0.2.dist-info/LICENSE
pybgpstream-2.0.2.dist-info/METADATA
pybgpstream-2.0.2.dist-info/WHEEL
pybgpstream-2.0.2.dist-info/top_level.txt
pybgpstream-2.0.2.dist-info/RECORD
