Metadata-Version: 2.1
Name: pybgpstream
Version: 2.0.2
Summary: A Python interface to BGPStream
Home-page: http://bgpstream.caida.org
Author: Alistair King
Author-email: bgpstream-info@caida.org
License: BSD
Keywords: _pybgpstream pybgpstream bgpstream bgp mrt routeviews route-views ris routing
Platform: UNKNOWN
Classifier: Development Status :: 5 - Production/Stable
Classifier: Environment :: Console
Classifier: Intended Audience :: Science/Research
Classifier: Intended Audience :: System Administrators
Classifier: Intended Audience :: Telecommunications Industry
Classifier: Intended Audience :: Information Technology
Classifier: License :: OSI Approved :: BSD License
Classifier: Operating System :: POSIX
Requires-Dist: python-dateutil
